iotile_support_prod_pod1m_0/__init__.py
iotile_support_prod_pod1m_0/calibrate_pod1m_step.py
iotile_support_prod_pod1m_0/reset_pod1m_step.py
iotile_support_prod_pod1m_0/tracker_app.py
iotile_support_prod_pod1m_0-0.3.11.dist-info/METADATA
iotile_support_prod_pod1m_0-0.3.11.dist-info/RECORD
iotile_support_prod_pod1m_0-0.3.11.dist-info/WHEEL
iotile_support_prod_pod1m_0-0.3.11.dist-info/entry_points.txt
iotile_support_prod_pod1m_0-0.3.11.dist-info/top_level.txt
