Metadata-Version: 2.1
Name: iotile-support-prod-pod1m-0
Version: 0.3.11
Summary: UNKNOWN
Home-page: UNKNOWN
Author: Arch
Author-email: info@arch-iot.com
License: UNKNOWN
Platform: UNKNOWN
Requires-Dist: iotile-support-con-nrf52832-2 (~=2.11.4)
Requires-Dist: iotile-support-firm-accelerometer-2 (~=2.3.1)
Requires-Dist: iotile-support-firm-env-1 (~=1.1.1)
Requires-Dist: numpy (>=1.15.1)
